odoo/addons/website_blog_excerpt_img/README.rst
odoo/addons/website_blog_excerpt_img/__init__.py
odoo/addons/website_blog_excerpt_img/__manifest__.py
odoo/addons/website_blog_excerpt_img/i18n/bg.po
odoo/addons/website_blog_excerpt_img/i18n/de.po
odoo/addons/website_blog_excerpt_img/i18n/el_GR.po
odoo/addons/website_blog_excerpt_img/i18n/es.po
odoo/addons/website_blog_excerpt_img/i18n/eu.po
odoo/addons/website_blog_excerpt_img/i18n/fr.po
odoo/addons/website_blog_excerpt_img/i18n/hr.po
odoo/addons/website_blog_excerpt_img/i18n/hr_HR.po
odoo/addons/website_blog_excerpt_img/i18n/it.po
odoo/addons/website_blog_excerpt_img/i18n/nb_NO.po
odoo/addons/website_blog_excerpt_img/i18n/pt_BR.po
odoo/addons/website_blog_excerpt_img/i18n/sl.po
odoo/addons/website_blog_excerpt_img/i18n/website_blog_excerpt_img.pot
odoo/addons/website_blog_excerpt_img/i18n/zh_CN.po
odoo/addons/website_blog_excerpt_img/models/__init__.py
odoo/addons/website_blog_excerpt_img/models/blog_post.py
odoo/addons/website_blog_excerpt_img/readme/CONTRIBUTORS.rst
odoo/addons/website_blog_excerpt_img/readme/DESCRIPTION.rst
odoo/addons/website_blog_excerpt_img/readme/INSTALL.rst
odoo/addons/website_blog_excerpt_img/readme/USAGE.rst
odoo/addons/website_blog_excerpt_img/static/description/icon.png
odoo/addons/website_blog_excerpt_img/static/description/index.html
odoo/addons/website_blog_excerpt_img/static/description/post-list.png
odoo/addons/website_blog_excerpt_img/templates/blog.xml
odoo/addons/website_blog_excerpt_img/templates/snippets.xml
odoo12_addon_website_blog_excerpt_img-12.0.1.2.0.dist-info/METADATA
odoo12_addon_website_blog_excerpt_img-12.0.1.2.0.dist-info/WHEEL
odoo12_addon_website_blog_excerpt_img-12.0.1.2.0.dist-info/top_level.txt
odoo12_addon_website_blog_excerpt_img-12.0.1.2.0.dist-info/RECORD
