Metadata-Version: 2.1
Name: odoo12-addon-website-blog-excerpt-img
Version: 12.0.1.2.0
Summary: New layout for blog posts list, and autoselect social share image when no cover is selected
Home-page: https://github.com/OCA/website
Author: Odoo Community Association (OCA), Tecnativa
Author-email: support@odoo-community.org
License: LGPL-3
Platform: UNKNOWN
Classifier: Programming Language :: Python
Classifier: Framework :: Odoo
Classifier: License :: OSI Approved :: GNU Lesser General Public License v3 (LGPLv3)
Requires-Python: >=3.5
Requires-Dist: odoo12-addon-html-image-url-extractor
Requires-Dist: odoo (<12.1dev,>=12.0a)
